iaversion/_version.cpython-313-i386-linux-musl.so
iaversion/__init__.cpython-313-i386-linux-musl.so
iaversion-0.0.3.dist-info/RECORD
iaversion-0.0.3.dist-info/WHEEL
iaversion-0.0.3.dist-info/top_level.txt
iaversion-0.0.3.dist-info/METADATA
