Metadata-Version: 2.1
Name: iaversion
Version: 0.0.3
Author-email: Innovations Anonymous <InnovAnon-Inc@gmx.com>
Requires-Python: >=3.11
Requires-Dist: iasimplesetup>=0.0.3
Requires-Dist: setuptools-scm
Requires-Dist: setuptools-scm-git-semver
